tex2py/__init__.py
tex2py/tex2py.py
tex2py-0.0.5.dist-info/LICENSE
tex2py-0.0.5.dist-info/METADATA
tex2py-0.0.5.dist-info/WHEEL
tex2py-0.0.5.dist-info/top_level.txt
tex2py-0.0.5.dist-info/RECORD
